whitebox/__init__.py
whitebox/cron.py
whitebox/main.py
whitebox/analytics/__init__.py
whitebox/analytics/tests/__init__.py
whitebox/analytics/tests/test_pipelines.py
whitebox/api/__init__.py
whitebox/api/v1/__init__.py
whitebox/api/v1/alerts.py
whitebox/api/v1/cron_tasks.py
whitebox/api/v1/dataset_rows.py
whitebox/api/v1/docs.py
whitebox/api/v1/drifting_metrics.py
whitebox/api/v1/health.py
whitebox/api/v1/inference_rows.py
whitebox/api/v1/model_integrity_metrics.py
whitebox/api/v1/model_monitors.py
whitebox/api/v1/models.py
whitebox/api/v1/performance_metrics.py
whitebox/core/__init__.py
whitebox/core/db.py
whitebox/core/manager.py
whitebox/core/settings.py
whitebox/crud/__init__.py
whitebox/crud/alerts.py
whitebox/crud/base.py
whitebox/crud/dataset_rows.py
whitebox/crud/drifting_metrics.py
whitebox/crud/inference_rows.py
whitebox/crud/model_integrity_metrics.py
whitebox/crud/model_monitors.py
whitebox/crud/models.py
whitebox/crud/performance_metrics.py
whitebox/crud/users.py
whitebox/entities/Alert.py
whitebox/entities/Base.py
whitebox/entities/DatasetRow.py
whitebox/entities/DriftingMetric.py
whitebox/entities/Inference.py
whitebox/entities/Model.py
whitebox/entities/ModelIntegrityMetric.py
whitebox/entities/ModelMonitor.py
whitebox/entities/PerformanceMetric.py
whitebox/entities/User.py
whitebox/entities/__init__.py
whitebox/schemas/__init__.py
whitebox/schemas/alert.py
whitebox/schemas/base.py
whitebox/schemas/datasetRow.py
whitebox/schemas/driftingMetric.py
whitebox/schemas/inferenceRow.py
whitebox/schemas/model.py
whitebox/schemas/modelIntegrityMetric.py
whitebox/schemas/modelMonitor.py
whitebox/schemas/performanceMetric.py
whitebox/schemas/task.py
whitebox/schemas/user.py
whitebox/schemas/utils.py
whitebox/sdk/__init__.py
whitebox/sdk/whitebox.py
whitebox/tests/__init__.py
whitebox/tests/v1/__init__.py
whitebox/tests/v1/conftest.py
whitebox/tests/v1/mock_data.py
whitebox/tests/v1/test_alerts.py
whitebox/tests/v1/test_cron_tasks.py
whitebox_sdk-0.0.20.dist-info/LICENCE
whitebox_sdk-0.0.20.dist-info/METADATA
whitebox_sdk-0.0.20.dist-info/WHEEL
whitebox_sdk-0.0.20.dist-info/top_level.txt
whitebox_sdk-0.0.20.dist-info/RECORD
